shapelets/__init__.py
shapelets/__main__.py
shapelets/_cli.py
shapelets/_version.py
shapelets/version.py
shapelets/compute/__basic_typing.py
shapelets/compute/__init__.py
shapelets/compute/_algorithms.py
shapelets/compute/_array_obj.py
shapelets/compute/_construction.py
shapelets/compute/_device.py
shapelets/compute/_extract_transform.py
shapelets/compute/_linear_algebra.py
shapelets/compute/_logic.py
shapelets/compute/_math.py
shapelets/compute/_pygauss.cp37-win_amd64.pyd
shapelets/compute/_statistics.py
shapelets/compute/clustering.py
shapelets/compute/dimensionality.py
shapelets/compute/distances.py
shapelets/compute/fft.py
shapelets/compute/matrixprofile.py
shapelets/compute/normalization.py
shapelets/compute/random.py
shapelets/compute/.libs/af.dll
shapelets/data/Coffee_TEST.txt
shapelets/data/Coffee_TRAIN.txt
shapelets/data/ItalianPowerDemand.mat
shapelets/data/Patient1.Mix 01.amc.txt
shapelets/data/Patient1.Mix 02.amc.txt
shapelets/data/__init__.py
shapelets/data/carpet_query.gz
shapelets/data/carpet_query.txt
shapelets/data/coffee_test.gz
shapelets/data/coffee_train.gz
shapelets/data/daily-min-temperatures.txt
shapelets/data/daily_min_temperatures.gz
shapelets/data/ecg-heartbeat-av.txt
shapelets/data/ecg_heartbeat_av.gz
shapelets/data/entoe_2016_es_day_ahead_prices.gz
shapelets/data/entoe_2016_es_load.gz
shapelets/data/entoe_2016_es_load_forecast.gz
shapelets/data/entoe_2016_es_solar_forecast.gz
shapelets/data/entoe_2016_es_wind_forecast.gz
shapelets/data/italian_power_demand.gz
shapelets/data/loader.py
shapelets/data/patient1_mix_01.gz
shapelets/data/patient1_mix_02.gz
shapelets/data/pig.gz
shapelets/data/pig.txt
shapelets/data/regime.gz
shapelets/data/regime.txt
shapelets/data/robot_dog.gz
shapelets/data/robot_dog.txt
shapelets/generators/__init__.py
shapelets/generators/controlcharts.py
shapelets_compute-0.3.1.dist-info/LICENSE.MD
shapelets_compute-0.3.1.dist-info/METADATA
shapelets_compute-0.3.1.dist-info/WHEEL
shapelets_compute-0.3.1.dist-info/entry_points.txt
shapelets_compute-0.3.1.dist-info/top_level.txt
shapelets_compute-0.3.1.dist-info/RECORD
