Metadata-Version: 2.1
Name: shapelets-compute
Version: 0.3.1
Summary: Shapelets Compute is an accelerated platform for time series analysis.
Home-page: https://shapelets.io
Author: Justo Ruiz Ferrer et al.
Author-email: info@shapelets.io
Maintainer: Shapelets Developers
Maintainer-email: info@shapelets.io
License: MIT
Download-URL: https://pypi.org/project/shapelets-compute/
Project-URL: Documentation, https:://shapelets.io/doc/dev
Platform: Windows,
Platform: Linux,
Platform: Mac OS,
Platform: Unix
Classifier: Development Status :: 3 - Alpha
Classifier: Intended Audience :: Science/Research
Classifier: Intended Audience :: Developers
Classifier: License :: OSI Approved :: BSD License
Classifier: Programming Language :: C
Classifier: Programming Language :: Python
Classifier: Programming Language :: Python :: 3
Classifier: Programming Language :: Python :: 3.7
Classifier: Programming Language :: Python :: 3.8
Classifier: Programming Language :: Python :: 3.9
Classifier: Programming Language :: Python :: 3 :: Only
Classifier: Programming Language :: Python :: Implementation :: CPython
Classifier: Topic :: Software Development
Classifier: Topic :: Scientific/Engineering
Classifier: Typing :: Typed
Classifier: Operating System :: Microsoft :: Windows
Classifier: Operating System :: Unix
Classifier: Operating System :: MacOS
Requires-Python: >=3.7
